brikk/cancel/__init__.py
brikk/cancel/_lib.py
brikk/cancel/_types.py
brikk/cancel/py.typed
brikk_cancel-0.2.1.dist-info/WHEEL
brikk_cancel-0.2.1.dist-info/METADATA
brikk_cancel-0.2.1.dist-info/RECORD
