Metadata-Version: 2.4
Name: brikk-cancel
Version: 0.2.1
Summary: brikk-cancel
Author: Lucino772
License-Expression: MIT
Requires-Python: >=3.10
